moveo_jokeapi_integrator-0.1.0.dist-info/METADATA
moveo_jokeapi_integrator-0.1.0.dist-info/WHEEL
moveo_jokeapi_integrator-0.1.0.dist-info/licenses/LICENSE
moveo_webhook/__init__.py
moveo_webhook/core.py
moveo_webhook/utils.py
moveo_jokeapi_integrator-0.1.0.dist-info/RECORD
