Metadata-Version: 2.1
Name: moveo-jokeapi-integrator
Version: 0.1.0
Summary: Library that integrates moveo's dialog's webhooks to jokeAPI (getJoke endpoint)
Author-Email: Jones Sabino <jones.sabino@gmail.com>
License: MIT
Requires-Python: >=3.12
Requires-Dist: requests>=2.32.3
Requires-Dist: pydantic>=2.8.2
Requires-Dist: fastapi>=0.111.1
Requires-Dist: python-box>=7.2.0
Requires-Dist: loguru>=0.7.2
